css.py
termstrap-1.2.4.dist-info/LICENSE
termstrap-1.2.4.dist-info/METADATA
termstrap-1.2.4.dist-info/WHEEL
termstrap-1.2.4.dist-info/top_level.txt
termstrap-1.2.4.dist-info/RECORD
