Metadata-Version: 2.1
Name: termstrap
Version: 1.2.4
Summary: Terminal Bootstrap - A Python css file for unicode text formatting in python console output
Home-page: https://github.com/t3chn0tr0n/termstrap
Author: t3chn0tr0n
Author-email: technotron.avik@gmail.com
License: UNKNOWN
Project-URL: Source, https://github.com/t3chn0tr0n/termstrap
Platform: UNKNOWN
Classifier: Programming Language :: Python :: 3
Classifier: Programming Language :: Python :: 3.5
Classifier: Programming Language :: Python :: 3.6
Classifier: Programming Language :: Python :: 3.7
Classifier: Intended Audience :: Developers
Classifier: License :: OSI Approved :: MIT License
Requires-Python: >=3.*.*
